<?xml version="1.0" encoding="UTF-8" ?>
<root>
  <id>d61fff1a-4ee2-4c0e-abef-9fcb353ed3bd</id>
  <name>Ken Pitts</name>
  <paid>5</paid>
  <backets>
    <bracket>
      <201>GONZ</201>
      <202>BOISE</202>
      <203>UCONN</203>
      <204>ARK</204>
      <205>BAMA</205>
      <206>TTU</206>
      <207>MSU</207>
      <208>DUKE</208>
      <209>BAY</209>
      <210>UNC</210>
      <211>STMARY</211>
      <212>UCLA</212>
      <213>TEXAS</213>
      <214>PUR</214>
      <215>MURR</215>
      <216>UK</216>
      <217>ZONA</217>
      <218>TCU</218>
      <219>HOU</219>
      <220>ILL</220>
      <221>CSU</221>
      <222>TENN</222>
      <223>OSU</223>
      <224>NOVA</224>
      <225>KANSAS</225>
      <226>SDSU</226>
      <227>IOWA</227>
      <228>PROV</228>
      <229>LSU</229>
      <230>WIS</230>
      <231>USC</231>
      <232>AUB</232>
      <301>GONZ</301>
      <302>UCONN</302>
      <303>TTU</303>
      <304>DUKE</304>
      <305>BAY</305>
      <306>UCLA</306>
      <307>PUR</307>
      <308>UK</308>
      <309>ZONA</309>
      <310>TCU</310>
      <311>TENN</311>
      <312>NOVA</312>
      <313>KANSAS</313>
      <314>IOWA</314>
      <315>LSU</315>
      <316>AUB</316>
      <401>GONZ</401>
      <402>DUKE</402>
      <403>UCLA</403>
      <404>UK</404>
      <405>ZONA</405>
      <406>TENN</406>
      <407>KANSAS</407>
      <408>AUB</408>
      <501>GONZ</501>
      <502>UK</502>
      <503>ZONA</503>
      <504>KANSAS</504>
      <601>GONZ</601>
      <602>KANSAS</602>
      <701>KANSAS</701>
    </bracket>
  </brackets>
</root>
